pit38/__init__.py
pit38/brokers/__init__.py
pit38/brokers/base.py
pit38/brokers/freedom24.py
pit38/brokers/utils.py
pit38/cli.py
pit38/exceptions.py
pit38/exchange/__init__.py
pit38/exchange/nbp.py
pit38/exchange/rates.py
pit38/io/__init__.py
pit38/io/utils.py
pit38/io/xlsx.py
pit38/main.py
pit38/models.py
pit38/positions/__init__.py
pit38/positions/profit_calculator.py
pit38/positions/trades_matcher.py
pit38/reports/__init__.py
pit38/reports/pit_8c.py
pit38/reports/templates/PIT-8C.pdf
pit38/reports/templates/PIT-8C.txt
pit38-0.0.2.dist-info/LICENSE
pit38-0.0.2.dist-info/METADATA
pit38-0.0.2.dist-info/WHEEL
pit38-0.0.2.dist-info/entry_points.txt
pit38-0.0.2.dist-info/RECORD
