Metadata-Version: 2.3
Name: pit38
Version: 0.0.2
Summary: A CLI tool that assists in preparing the PIT-38 declaration based on the annual tax reports from your broker
License: MIT
Author: Ihar Yazerski
Author-email: ihar.yazerski@gmail.com
Requires-Python: >=3.10
Classifier: Programming Language :: Python :: 3
Classifier: License :: OSI Approved :: MIT License
Classifier: Operating System :: OS Independent
Requires-Dist: openpyxl (>=3.1.5,<4.0.0)
Requires-Dist: pydantic (>=2.10.5,<3.0.0)
Requires-Dist: pypdf (>=5.1.0,<6.0.0)
Requires-Dist: requests (>=2.32.3,<3.0.0)
Requires-Dist: typer[all] (>=0.15.1,<0.16.0)
Project-URL: Homepage, https://github.com/iyazerski/pit38
